<rdf:RDF xmlns:dams="http://library.ucsd.edu/ontology/dams#"
         xmlns:rdf="http://www.w3.org/1999/02/22-rdf-syntax-ns#">
  <dams:ScopeContentNote rdf:about="http://library.ucsd.edu/ark:/20775/bd1366006j">
    <dams:type>scope_and_content</dams:type>
    <dams:displayLabel>Scope and contents</dams:displayLabel>
    <rdf:value>Electronic theses and dissertations submitted by UC San Diego students as part of their degree requirements and representing all UC San Diego academic programs.</rdf:value>
  </dams:ScopeContentNote>
</rdf:RDF>
